{
  "name": "",
  "data": {
    "College accommodation": {},
    "Catering": {
      "Dining hall": true,
      "Bar": true,
      "Café": true
    },
    "Facilities": {
      "Gym on site": true,
      "Boathouse": true,
      "Library open 24/7": true,
      "Computer rooms/stations": true,
      "Wi-Fi throughout college": true,
      "Music room": true,
      "Theatre/performance space": false,
      "Chapel": true,
      "Multi-faith prayer room": true
    },
    "Clubs and societies": {
      "Music society": true,
      "Orchestra/s": true,
      "Choir/s": true,
      "Dramatic society": true,
      "College student magazine/paper": true,
      "Some subject societies": true,
      "Other societies": true
    }
  }
}